{
  "generatedAt": "2025-12-29T16:35:37.236Z",
  "scheduleSlot": "evening",
  "post": {
    "type": "statistic",
    "title": "游늳 China tiene 50% m치s papers de IA que EEUU",
    "content": "游늳 China tiene 50% m치s papers de IA que EEUU\n\nFuente: Stanford AI Index 2024",
    "contentLong": "游늳 Dato del d칤a sobre IA\n\nChina tiene 50% m치s papers de IA que EEUU\n\n游늵 Fuente: Stanford AI Index 2024\n\n游댕 M치s insights en mbainative.com",
    "hashtags": [
      "IA",
      "InteligenciaArtificial",
      "MBAINative",
      "EmpresaAINativa",
      "ChinaIA",
      "InvestigacionIA"
    ],
    "url": "https://mbainative.com",
    "imageUrl": null
  }
}