{
  "generatedAt": "2026-03-15T11:21:07.411Z",
  "scheduleSlot": "noon",
  "principle": {
    "id": 15,
    "title": "Mejora continua automatizada",
    "icon": "🔄"
  },
  "post": {
    "type": "guru_quote",
    "content": "🔄 Principio #15: Mejora continua automatizada\n\n🧠 Jensen Huang (NVIDIA)\n\n\"NVIDIA CEO Champions AI “Digital Employees” for a New Era of Innovation\"\n\n▶️ youtube.com/watch?v=CJoTwEqA-gI",
    "hashtags": [
      "IA",
      "InteligenciaArtificial",
      "MBAINative",
      "GurusIA",
      "jensenhuang"
    ],
    "url": "https://youtube.com/watch?v=CJoTwEqA-gI",
    "imageUrl": "https://i.ytimg.com/vi/CJoTwEqA-gI/mqdefault.jpg"
  }
}